stableagents/__init__.py
stableagents/ai_providers.py
stableagents/cli.py
stableagents/cli_entry.py
stableagents/computer.py
stableagents/core/__init__.py
stableagents/core/ascii_art.py
stableagents/core/logging.py
stableagents/core/self_healing/__init__.py
stableagents/core/self_healing/controller.py
stableagents/core/self_healing/diagnosis.py
stableagents/core/self_healing/monitor.py
stableagents/core/self_healing/recovery.py
stableagents/desktop.py
stableagents/logic/mcp.py
stableagents/main.py
stableagents/memory/__init__.py
stableagents/memory/main.py
stableagents/run_cli.py
stableagents/simple_cli.py
stableagents/stableagents
stableagents/unified_cli.py
stableagents/utils/__init__.py
stableagents/utils/logging.py
stableagents_ai-0.3.0.dist-info/LICENSE
stableagents_ai-0.3.0.dist-info/METADATA
stableagents_ai-0.3.0.dist-info/WHEEL
stableagents_ai-0.3.0.dist-info/entry_points.txt
stableagents_ai-0.3.0.dist-info/RECORD
