Metadata-Version: 2.1
Name: stableagents-ai
Version: 0.3.0
Summary: A framework for self healing agents that can run locally and minimize hallucinations
License: MIT
Author: Your Name
Author-email: your.email@example.com
Requires-Python: >=3.9,<4.0
Classifier: Development Status :: 3 - Alpha
Classifier: Intended Audience :: Developers
Classifier: License :: OSI Approved :: MIT License
Classifier: Programming Language :: Python :: 3
Classifier: Programming Language :: Python :: 3.9
Classifier: Programming Language :: Python :: 3.10
Classifier: Programming Language :: Python :: 3.11
Classifier: Programming Language :: Python :: 3.12
Provides-Extra: all
Provides-Extra: desktop
Provides-Extra: local
Provides-Extra: self-healing
Requires-Dist: anthropic (>=0.5.0,<0.6.0)
Requires-Dist: llama-cpp-python (>=0.2.0,<0.3.0) ; extra == "local" or extra == "all"
Requires-Dist: openai (>=1.0.0,<2.0.0)
Requires-Dist: psutil (>=5.9.0,<6.0.0) ; extra == "self-healing" or extra == "all"
Requires-Dist: pyppeteer (>=1.0.2,<2.0.0) ; extra == "desktop" or extra == "all"
Requires-Dist: requests (>=2.28.0,<3.0.0)
